<?xml version="1.0" encoding="UTF-8"?>
<!--
 ! Source code generated by Celerio, a Jaxio product.
 ! Documentation: http://www.jaxio.com/documentation/celerio/
 ! Follow us on twitter: @jaxiosoft
 ! Need commercial support ? Contact us: info@jaxio.com
 ! Template pack-backend-jpa:src/main/resources/localization/domain/domain.e.vm.xml
 ! Template is part of Open Source Project: https://github.com/jaxio/pack-backend-jpa
-->
<!DOCTYPE properties SYSTEM "http://java.sun.com/dtd/properties.dtd">
<properties>
	<comment>Domain resources for CastMember</comment>

	<entry key="castMember">Cast Member</entry>
	<entry key="castMember_search">Search Cast Member</entry>
	<entry key="castMember_create">Create Cast Member</entry>
	<entry key="castMember_edit">Edit {0}</entry>
	<entry key="castMember_view">View {0}</entry>

	<!-- attributes -->
	<entry key="castMember_id">Id</entry>
	<entry key="castMember_artistId">Artist Id</entry>
	<entry key="castMember_typeId">Type Id</entry>
	<entry key="castMember_showId">Show Id</entry>

	<!-- x-to-one -->
	<entry key="castMember_artist">Artist</entry>
	<entry key="castMember_type">Type</entry>
	<entry key="castMember_show">Show</entry>

	<!-- uniques -->
	<entry key="castMember_composite_unique_constraint_error">A composite unique constraint has failed on Cast Member</entry>
</properties>